picarta/__init__.py
picarta/picarta.py
tests/__init__.py
tests/test_picarta.py
picarta-1.1.3.dist-info/METADATA
picarta-1.1.3.dist-info/WHEEL
picarta-1.1.3.dist-info/entry_points.txt
picarta-1.1.3.dist-info/top_level.txt
picarta-1.1.3.dist-info/RECORD
