Metadata-Version: 2.1
Name: picarta
Version: 1.1.3
Summary: A package to geolocate images from URL or local files using Picarta AI
Home-page: https://github.com/PicartaAI/Picarta-API
Author: Picarta
Author-email: info@picarta.ai
Classifier: Programming Language :: Python :: 3
Classifier: License :: OSI Approved :: MIT License
Classifier: Operating System :: OS Independent
Requires-Python: >=3.6
Requires-Dist: requests
Requires-Dist: pillow
Requires-Dist: simplekml ==1.3.6
